marshmallow_mongoengine/__init__.py
marshmallow_mongoengine/convert.py
marshmallow_mongoengine/exceptions.py
marshmallow_mongoengine/fields.py
marshmallow_mongoengine/schema.py
marshmallow_mongoengine/conversion/__init__.py
marshmallow_mongoengine/conversion/fields.py
marshmallow_mongoengine/conversion/params.py
marshmallow_mongoengine-0.31.2.dist-info/LICENSE
marshmallow_mongoengine-0.31.2.dist-info/METADATA
marshmallow_mongoengine-0.31.2.dist-info/WHEEL
marshmallow_mongoengine-0.31.2.dist-info/top_level.txt
marshmallow_mongoengine-0.31.2.dist-info/RECORD
