Metadata-Version: 1.1
Name: marshmallow-mongoengine
Version: 0.31.2
Summary: Mongoengine integration with the marshmallow (de)serialization library
Home-page: https://github.com/MongoEngine/marshmallow-mongoengine
Author: Emmanuel Leblond, Patrick Huck
Author-email: phuck@lbl.gov
License: MIT
Keywords: mongoengine marshmallow
Platform: UNKNOWN
Classifier: Intended Audience :: Developers
Classifier: License :: OSI Approved :: MIT License
Classifier: Natural Language :: English
Classifier: Programming Language :: Python :: 3
Classifier: Programming Language :: Python :: 3.4
Classifier: Programming Language :: Python :: 3.5
Classifier: Programming Language :: Python :: 3.6
Classifier: Programming Language :: Python :: 3.7
Classifier: Programming Language :: Python :: 3.8
